[
  {
    "account": {
      "accountCode": 10100
    },
    "amountUnit": 1000,
    "debit": {
      "formatted": "3,161,007",
      "amount": 3161007000
    },
    "credit": {
      "formatted": "0",
      "amount": 0
    }
  },
  {
    "account": {
      "accountCode": 10101
    },
    "amountUnit": 1000,
    "debit": {
      "formatted": "25,431",
      "amount": 25430750
    },
    "credit": {
      "formatted": "0",
      "amount": 0
    }
  },
  {
    "account": {
      "accountCode": 10102
    },
    "amountUnit": 1000,
    "debit": {
      "formatted": "27,434",
      "amount": 27434320
    },
    "credit": {
      "formatted": "0",
      "amount": 0
    }
  },
  {
    "account": {
      "accountCode": 10103
    },
    "amountUnit": 1000,
    "debit": {
      "formatted": "18,640",
      "amount": 18639880
    },
    "credit": {
      "formatted": "0",
      "amount": 0
    }
  },
  {
    "account": {
      "accountCode": 10104
    },
    "amountUnit": 1000,
    "debit": {
      "formatted": "7,481",
      "amount": 7480760
    },
    "credit": {
      "formatted": "0",
      "amount": 0
    }
  },
  {
    "account": {
      "accountCode": 10105
    },
    "amountUnit": 1000,
    "debit": {
      "formatted": "0",
      "amount": 0
    },
    "credit": {
      "formatted": "0",
      "amount": 0
    }
  },
  {
    "account": {
      "accountCode": 10106
    },
    "amountUnit": 1000,
    "debit": {
      "formatted": "0",
      "amount": 0
    },
    "credit": {
      "formatted": "0",
      "amount": 0
    }
  },
  {
    "account": {
      "accountCode": 10107
    },
    "amountUnit": 1000,
    "debit": {
      "formatted": "0",
      "amount": 0
    },
    "credit": {
      "formatted": "0",
      "amount": 0
    }
  },
  {
    "account": {
      "accountCode": 10108
    },
    "amountUnit": 1000,
    "debit": {
      "formatted": "0",
      "amount": 0
    },
    "credit": {
      "formatted": "0",
      "amount": 0
    }
  },
  {
    "account": {
      "accountCode": 10120
    },
    "amountUnit": 1000,
    "debit": {
      "formatted": "0",
      "amount": 0
    },
    "credit": {
      "formatted": "0",
      "amount": 0
    }
  },
  {
    "account": {
      "accountCode": 10130
    },
    "amountUnit": 1000,
    "debit": {
      "formatted": "69,240",
      "amount": 69240000
    },
    "credit": {
      "formatted": "0",
      "amount": 0
    }
  },
  {
    "account": {
      "accountCode": 10140
    },
    "amountUnit": 1000,
    "debit": {
      "formatted": "375",
      "amount": 375400
    },
    "credit": {
      "formatted": "0",
      "amount": 0
    }
  },
  {
    "account": {
      "accountCode": 10210
    },
    "amountUnit": 1000,
    "debit": {
      "formatted": "0",
      "amount": 0
    },
    "credit": {
      "formatted": "0",
      "amount": 0
    }
  },
  {
    "account": {
      "accountCode": 10220
    },
    "amountUnit": 1000,
    "debit": {
      "formatted": "0",
      "amount": 0
    },
    "credit": {
      "formatted": "0",
      "amount": 0
    }
  },
  {
    "account": {
      "accountCode": 10230
    },
    "amountUnit": 1000,
    "debit": {
      "formatted": "0",
      "amount": 0
    },
    "credit": {
      "formatted": "0",
      "amount": 0
    }
  },
  {
    "account": {
      "accountCode": 10240
    },
    "amountUnit": 1000,
    "debit": {
      "formatted": "5,746,580",
      "amount": 5746580470
    },
    "credit": {
      "formatted": "0",
      "amount": 0
    }
  },
  {
    "account": {
      "accountCode": 10250
    },
    "amountUnit": 1000,
    "debit": {
      "formatted": "0",
      "amount": 0
    },
    "credit": {
      "formatted": "0",
      "amount": 0
    }
  },
  {
    "account": {
      "accountCode": 10260
    },
    "amountUnit": 1000,
    "debit": {
      "formatted": "0",
      "amount": 0
    },
    "credit": {
      "formatted": "0",
      "amount": 0
    }
  },
  {
    "account": {
      "accountCode": 10275
    },
    "amountUnit": 1000,
    "debit": {
      "formatted": "0",
      "amount": 0
    },
    "credit": {
      "formatted": "0",
      "amount": 0
    }
  },
  {
    "account": {
      "accountCode": 10310
    },
    "amountUnit": 1000,
    "debit": {
      "formatted": "5,329,873",
      "amount": 5329872940
    },
    "credit": {
      "formatted": "0",
      "amount": 0
    }
  },
  {
    "account": {
      "accountCode": 10320
    },
    "amountUnit": 1000,
    "debit": {
      "formatted": "200,000",
      "amount": 200000000
    },
    "credit": {
      "formatted": "0",
      "amount": 0
    }
  },
  {
    "account": {
      "accountCode": 10330
    },
    "amountUnit": 1000,
    "debit": {
      "formatted": "105,644",
      "amount": 105644400
    },
    "credit": {
      "formatted": "0",
      "amount": 0
    }
  },
  {
    "account": {
      "accountCode": 10331
    },
    "amountUnit": 1000,
    "debit": {
      "formatted": "530,965",
      "amount": 530965490
    },
    "credit": {
      "formatted": "0",
      "amount": 0
    }
  },
  {
    "account": {
      "accountCode": 10340
    },
    "amountUnit": 1000,
    "debit": {
      "formatted": "0",
      "amount": 0
    },
    "credit": {
      "formatted": "0",
      "amount": 0
    }
  },
  {
    "account": {
      "accountCode": 10390
    },
    "amountUnit": 1000,
    "debit": {
      "formatted": "0",
      "amount": 0
    },
    "credit": {
      "formatted": "0",
      "amount": 0
    }
  },
  {
    "account": {
      "accountCode": 10405
    },
    "amountUnit": 1000,
    "debit": {
      "formatted": "30,981,601",
      "amount": 30981600760
    },
    "credit": {
      "formatted": "0",
      "amount": 0
    }
  },
  {
    "account": {
      "accountCode": 10410
    },
    "amountUnit": 1000,
    "debit": {
      "formatted": "0",
      "amount": 0
    },
    "credit": {
      "formatted": "0",
      "amount": 0
    }
  },
  {
    "account": {
      "accountCode": 10420
    },
    "amountUnit": 1000,
    "debit": {
      "formatted": "12,714",
      "amount": 12713740
    },
    "credit": {
      "formatted": "0",
      "amount": 0
    }
  },
  {
    "account": {
      "accountCode": 10430
    },
    "amountUnit": 1000,
    "debit": {
      "formatted": "1,025,516",
      "amount": 1025516030
    },
    "credit": {
      "formatted": "0",
      "amount": 0
    }
  },
  {
    "account": {
      "accountCode": 10440
    },
    "amountUnit": 1000,
    "debit": {
      "formatted": "0",
      "amount": 0
    },
    "credit": {
      "formatted": "0",
      "amount": 0
    }
  },
  {
    "account": {
      "accountCode": 10490
    },
    "amountUnit": 1000,
    "debit": {
      "formatted": "0",
      "amount": 0
    },
    "credit": {
      "formatted": "0",
      "amount": 0
    }
  },
  {
    "account": {
      "accountCode": 11000
    },
    "amountUnit": 1000,
    "debit": {
      "formatted": "0",
      "amount": 0
    },
    "credit": {
      "formatted": "0",
      "amount": 0
    }
  },
  {
    "account": {
      "accountCode": 11010
    },
    "amountUnit": 1000,
    "debit": {
      "formatted": "0",
      "amount": 0
    },
    "credit": {
      "formatted": "0",
      "amount": 0
    }
  },
  {
    "account": {
      "accountCode": 11030
    },
    "amountUnit": 1000,
    "debit": {
      "formatted": "0",
      "amount": 0
    },
    "credit": {
      "formatted": "0",
      "amount": 0
    }
  },
  {
    "account": {
      "accountCode": 11070
    },
    "amountUnit": 1000,
    "debit": {
      "formatted": "0",
      "amount": 0
    },
    "credit": {
      "formatted": "0",
      "amount": 0
    }
  },
  {
    "account": {
      "accountCode": 11110
    },
    "amountUnit": 1000,
    "debit": {
      "formatted": "2,803,773",
      "amount": 2803773230
    },
    "credit": {
      "formatted": "0",
      "amount": 0
    }
  },
  {
    "account": {
      "accountCode": 11120
    },
    "amountUnit": 1000,
    "debit": {
      "formatted": "15,463",
      "amount": 15463380
    },
    "credit": {
      "formatted": "0",
      "amount": 0
    }
  },
  {
    "account": {
      "accountCode": 11130
    },
    "amountUnit": 1000,
    "debit": {
      "formatted": "0",
      "amount": 0
    },
    "credit": {
      "formatted": "0",
      "amount": 0
    }
  },
  {
    "account": {
      "accountCode": 11170
    },
    "amountUnit": 1000,
    "debit": {
      "formatted": "0",
      "amount": 0
    },
    "credit": {
      "formatted": "185,408",
      "amount": 185408210
    }
  },
  {
    "account": {
      "accountCode": 11200
    },
    "amountUnit": 1000,
    "debit": {
      "formatted": "225,000",
      "amount": 225000000
    },
    "credit": {
      "formatted": "0",
      "amount": 0
    }
  },
  {
    "account": {
      "accountCode": 11210
    },
    "amountUnit": 1000,
    "debit": {
      "formatted": "0",
      "amount": 0
    },
    "credit": {
      "formatted": "0",
      "amount": 0
    }
  },
  {
    "account": {
      "accountCode": 11230
    },
    "amountUnit": 1000,
    "debit": {
      "formatted": "0",
      "amount": 0
    },
    "credit": {
      "formatted": "0",
      "amount": 0
    }
  },
  {
    "account": {
      "accountCode": 11270
    },
    "amountUnit": 1000,
    "debit": {
      "formatted": "21,611",
      "amount": 21611250
    },
    "credit": {
      "formatted": "0",
      "amount": 0
    }
  },
  {
    "account": {
      "accountCode": 11300
    },
    "amountUnit": 1000,
    "debit": {
      "formatted": "25,301,334",
      "amount": 25301333730
    },
    "credit": {
      "formatted": "0",
      "amount": 0
    }
  },
  {
    "account": {
      "accountCode": 11310
    },
    "amountUnit": 1000,
    "debit": {
      "formatted": "799,993",
      "amount": 799993000
    },
    "credit": {
      "formatted": "0",
      "amount": 0
    }
  },
  {
    "account": {
      "accountCode": 11330
    },
    "amountUnit": 1000,
    "debit": {
      "formatted": "0",
      "amount": 0
    },
    "credit": {
      "formatted": "1,294",
      "amount": 1294270
    }
  },
  {
    "account": {
      "accountCode": 11370
    },
    "amountUnit": 1000,
    "debit": {
      "formatted": "0",
      "amount": 0
    },
    "credit": {
      "formatted": "295,546",
      "amount": 295545950
    }
  },
  {
    "account": {
      "accountCode": 11380
    },
    "amountUnit": 1000,
    "debit": {
      "formatted": "9,164,681",
      "amount": 9164680740
    },
    "credit": {
      "formatted": "0",
      "amount": 0
    }
  },
  {
    "account": {
      "accountCode": 11385
    },
    "amountUnit": 1000,
    "debit": {
      "formatted": "346,829",
      "amount": 346828940
    },
    "credit": {
      "formatted": "0",
      "amount": 0
    }
  },
  {
    "account": {
      "accountCode": 11390
    },
    "amountUnit": 1000,
    "debit": {
      "formatted": "0",
      "amount": 0
    },
    "credit": {
      "formatted": "0",
      "amount": 0
    }
  },
  {
    "account": {
      "accountCode": 11400
    },
    "amountUnit": 1000,
    "debit": {
      "formatted": "29,703,357",
      "amount": 29703357200
    },
    "credit": {
      "formatted": "0",
      "amount": 0
    }
  },
  {
    "account": {
      "accountCode": 11410
    },
    "amountUnit": 1000,
    "debit": {
      "formatted": "395,924",
      "amount": 395924350
    },
    "credit": {
      "formatted": "0",
      "amount": 0
    }
  },
  {
    "account": {
      "accountCode": 11430
    },
    "amountUnit": 1000,
    "debit": {
      "formatted": "0",
      "amount": 0
    },
    "credit": {
      "formatted": "4,973",
      "amount": 4972630
    }
  },
  {
    "account": {
      "accountCode": 11470
    },
    "amountUnit": 1000,
    "debit": {
      "formatted": "0",
      "amount": 0
    },
    "credit": {
      "formatted": "1,214,359",
      "amount": 1214359040
    }
  },
  {
    "account": {
      "accountCode": 11480
    },
    "amountUnit": 1000,
    "debit": {
      "formatted": "0",
      "amount": 0
    },
    "credit": {
      "formatted": "0",
      "amount": 0
    }
  },
  {
    "account": {
      "accountCode": 11485
    },
    "amountUnit": 1000,
    "debit": {
      "formatted": "0",
      "amount": 0
    },
    "credit": {
      "formatted": "0",
      "amount": 0
    }
  },
  {
    "account": {
      "accountCode": 11490
    },
    "amountUnit": 1000,
    "debit": {
      "formatted": "0",
      "amount": 0
    },
    "credit": {
      "formatted": "0",
      "amount": 0
    }
  },
  {
    "account": {
      "accountCode": 11610
    },
    "amountUnit": 1000,
    "debit": {
      "formatted": "0",
      "amount": 0
    },
    "credit": {
      "formatted": "0",
      "amount": 0
    }
  },
  {
    "account": {
      "accountCode": 11615
    },
    "amountUnit": 1000,
    "debit": {
      "formatted": "0",
      "amount": 0
    },
    "credit": {
      "formatted": "0",
      "amount": 0
    }
  },
  {
    "account": {
      "accountCode": 12010
    },
    "amountUnit": 1000,
    "debit": {
      "formatted": "13,446,737",
      "amount": 13446736900
    },
    "credit": {
      "formatted": "0",
      "amount": 0
    }
  },
  {
    "account": {
      "accountCode": 12015
    },
    "amountUnit": 1000,
    "debit": {
      "formatted": "13,132,988",
      "amount": 13132987870
    },
    "credit": {
      "formatted": "0",
      "amount": 0
    }
  },
  {
    "account": {
      "accountCode": 12016
    },
    "amountUnit": 1000,
    "debit": {
      "formatted": "0",
      "amount": 0
    },
    "credit": {
      "formatted": "0",
      "amount": 0
    }
  },
  {
    "account": {
      "accountCode": 12017
    },
    "amountUnit": 1000,
    "debit": {
      "formatted": "55,232",
      "amount": 55231880
    },
    "credit": {
      "formatted": "0",
      "amount": 0
    }
  },
  {
    "account": {
      "accountCode": 12020
    },
    "amountUnit": 1000,
    "debit": {
      "formatted": "10,449",
      "amount": 10448770
    },
    "credit": {
      "formatted": "0",
      "amount": 0
    }
  },
  {
    "account": {
      "accountCode": 12025
    },
    "amountUnit": 1000,
    "debit": {
      "formatted": "0",
      "amount": 0
    },
    "credit": {
      "formatted": "0",
      "amount": 0
    }
  },
  {
    "account": {
      "accountCode": 12030
    },
    "amountUnit": 1000,
    "debit": {
      "formatted": "736,555",
      "amount": 736555390
    },
    "credit": {
      "formatted": "0",
      "amount": 0
    }
  },
  {
    "account": {
      "accountCode": 12035
    },
    "amountUnit": 1000,
    "debit": {
      "formatted": "0",
      "amount": 0
    },
    "credit": {
      "formatted": "0",
      "amount": 0
    }
  },
  {
    "account": {
      "accountCode": 12075
    },
    "amountUnit": 1000,
    "debit": {
      "formatted": "56,265",
      "amount": 56264870
    },
    "credit": {
      "formatted": "0",
      "amount": 0
    }
  },
  {
    "account": {
      "accountCode": 12110
    },
    "amountUnit": 1000,
    "debit": {
      "formatted": "2,403,054",
      "amount": 2403054170
    },
    "credit": {
      "formatted": "0",
      "amount": 0
    }
  },
  {
    "account": {
      "accountCode": 12115
    },
    "amountUnit": 1000,
    "debit": {
      "formatted": "0",
      "amount": 0
    },
    "credit": {
      "formatted": "0",
      "amount": 0
    }
  },
  {
    "account": {
      "accountCode": 12120
    },
    "amountUnit": 1000,
    "debit": {
      "formatted": "144,804",
      "amount": 144803690
    },
    "credit": {
      "formatted": "0",
      "amount": 0
    }
  },
  {
    "account": {
      "accountCode": 12130
    },
    "amountUnit": 1000,
    "debit": {
      "formatted": "0",
      "amount": 0
    },
    "credit": {
      "formatted": "0",
      "amount": 0
    }
  },
  {
    "account": {
      "accountCode": 12135
    },
    "amountUnit": 1000,
    "debit": {
      "formatted": "0",
      "amount": 0
    },
    "credit": {
      "formatted": "0",
      "amount": 0
    }
  },
  {
    "account": {
      "accountCode": 12140
    },
    "amountUnit": 1000,
    "debit": {
      "formatted": "0",
      "amount": 0
    },
    "credit": {
      "formatted": "0",
      "amount": 0
    }
  },
  {
    "account": {
      "accountCode": 12175
    },
    "amountUnit": 1000,
    "debit": {
      "formatted": "0",
      "amount": 0
    },
    "credit": {
      "formatted": "0",
      "amount": 0
    }
  },
  {
    "account": {
      "accountCode": 12210
    },
    "amountUnit": 1000,
    "debit": {
      "formatted": "0",
      "amount": 0
    },
    "credit": {
      "formatted": "0",
      "amount": 0
    }
  },
  {
    "account": {
      "accountCode": 12215
    },
    "amountUnit": 1000,
    "debit": {
      "formatted": "2,108,488",
      "amount": 2108487890.0000002
    },
    "credit": {
      "formatted": "0",
      "amount": 0
    }
  },
  {
    "account": {
      "accountCode": 12217
    },
    "amountUnit": 1000,
    "debit": {
      "formatted": "1,233,626",
      "amount": 1233625760
    },
    "credit": {
      "formatted": "0",
      "amount": 0
    }
  },
  {
    "account": {
      "accountCode": 12220
    },
    "amountUnit": 1000,
    "debit": {
      "formatted": "195,888,860",
      "amount": 195888860070
    },
    "credit": {
      "formatted": "0",
      "amount": 0
    }
  },
  {
    "account": {
      "accountCode": 12224
    },
    "amountUnit": 1000,
    "debit": {
      "formatted": "0",
      "amount": 0
    },
    "credit": {
      "formatted": "0",
      "amount": 0
    }
  },
  {
    "account": {
      "accountCode": 12225
    },
    "amountUnit": 1000,
    "debit": {
      "formatted": "5,658,060",
      "amount": 5658060300
    },
    "credit": {
      "formatted": "0",
      "amount": 0
    }
  },
  {
    "account": {
      "accountCode": 12226
    },
    "amountUnit": 1000,
    "debit": {
      "formatted": "250,000",
      "amount": 250000000
    },
    "credit": {
      "formatted": "0",
      "amount": 0
    }
  },
  {
    "account": {
      "accountCode": 12227
    },
    "amountUnit": 1000,
    "debit": {
      "formatted": "178,829,431",
      "amount": 178829431280
    },
    "credit": {
      "formatted": "0",
      "amount": 0
    }
  },
  {
    "account": {
      "accountCode": 12228
    },
    "amountUnit": 1000,
    "debit": {
      "formatted": "1,588,876",
      "amount": 1588876440
    },
    "credit": {
      "formatted": "0",
      "amount": 0
    }
  },
  {
    "account": {
      "accountCode": 12231
    },
    "amountUnit": 1000,
    "debit": {
      "formatted": "0",
      "amount": 0
    },
    "credit": {
      "formatted": "0",
      "amount": 0
    }
  },
  {
    "account": {
      "accountCode": 12232
    },
    "amountUnit": 1000,
    "debit": {
      "formatted": "77,300",
      "amount": 77300000
    },
    "credit": {
      "formatted": "0",
      "amount": 0
    }
  },
  {
    "account": {
      "accountCode": 12235
    },
    "amountUnit": 1000,
    "debit": {
      "formatted": "32,053,073",
      "amount": 32053073340
    },
    "credit": {
      "formatted": "0",
      "amount": 0
    }
  },
  {
    "account": {
      "accountCode": 12237
    },
    "amountUnit": 1000,
    "debit": {
      "formatted": "1,000,000",
      "amount": 1000000000
    },
    "credit": {
      "formatted": "0",
      "amount": 0
    }
  },
  {
    "account": {
      "accountCode": 12240
    },
    "amountUnit": 1000,
    "debit": {
      "formatted": "96,522,460",
      "amount": 96522460100
    },
    "credit": {
      "formatted": "0",
      "amount": 0
    }
  },
  {
    "account": {
      "accountCode": 12243
    },
    "amountUnit": 1000,
    "debit": {
      "formatted": "0",
      "amount": 0
    },
    "credit": {
      "formatted": "0",
      "amount": 0
    }
  },
  {
    "account": {
      "accountCode": 12245
    },
    "amountUnit": 1000,
    "debit": {
      "formatted": "9,585,845",
      "amount": 9585845230
    },
    "credit": {
      "formatted": "0",
      "amount": 0
    }
  },
  {
    "account": {
      "accountCode": 12260
    },
    "amountUnit": 1000,
    "debit": {
      "formatted": "0",
      "amount": 0
    },
    "credit": {
      "formatted": "0",
      "amount": 0
    }
  },
  {
    "account": {
      "accountCode": 12265
    },
    "amountUnit": 1000,
    "debit": {
      "formatted": "0",
      "amount": 0
    },
    "credit": {
      "formatted": "4,667,273",
      "amount": 4667272800
    }
  },
  {
    "account": {
      "accountCode": 12266
    },
    "amountUnit": 1000,
    "debit": {
      "formatted": "0",
      "amount": 0
    },
    "credit": {
      "formatted": "89,871,404",
      "amount": 89871404140
    }
  },
  {
    "account": {
      "accountCode": 12267
    },
    "amountUnit": 1000,
    "debit": {
      "formatted": "0",
      "amount": 0
    },
    "credit": {
      "formatted": "0",
      "amount": 0
    }
  },
  {
    "account": {
      "accountCode": 12268
    },
    "amountUnit": 1000,
    "debit": {
      "formatted": "0",
      "amount": 0
    },
    "credit": {
      "formatted": "0",
      "amount": 0
    }
  },
  {
    "account": {
      "accountCode": 12274
    },
    "amountUnit": 1000,
    "debit": {
      "formatted": "0",
      "amount": 0
    },
    "credit": {
      "formatted": "0",
      "amount": 0
    }
  },
  {
    "account": {
      "accountCode": 12275
    },
    "amountUnit": 1000,
    "debit": {
      "formatted": "1,424,593",
      "amount": 1424592760
    },
    "credit": {
      "formatted": "0",
      "amount": 0
    }
  },
  {
    "account": {
      "accountCode": 12277
    },
    "amountUnit": 1000,
    "debit": {
      "formatted": "0",
      "amount": 0
    },
    "credit": {
      "formatted": "0",
      "amount": 0
    }
  },
  {
    "account": {
      "accountCode": 12310
    },
    "amountUnit": 1000,
    "debit": {
      "formatted": "0",
      "amount": 0
    },
    "credit": {
      "formatted": "0",
      "amount": 0
    }
  },
  {
    "account": {
      "accountCode": 12315
    },
    "amountUnit": 1000,
    "debit": {
      "formatted": "0",
      "amount": 0
    },
    "credit": {
      "formatted": "0",
      "amount": 0
    }
  },
  {
    "account": {
      "accountCode": 12320
    },
    "amountUnit": 1000,
    "debit": {
      "formatted": "0",
      "amount": 0
    },
    "credit": {
      "formatted": "0",
      "amount": 0
    }
  },
  {
    "account": {
      "accountCode": 12325
    },
    "amountUnit": 1000,
    "debit": {
      "formatted": "7,977,157",
      "amount": 7977157100
    },
    "credit": {
      "formatted": "0",
      "amount": 0
    }
  },
  {
    "account": {
      "accountCode": 12327
    },
    "amountUnit": 1000,
    "debit": {
      "formatted": "248,027",
      "amount": 248026500
    },
    "credit": {
      "formatted": "0",
      "amount": 0
    }
  },
  {
    "account": {
      "accountCode": 12328
    },
    "amountUnit": 1000,
    "debit": {
      "formatted": "7,038",
      "amount": 7037530
    },
    "credit": {
      "formatted": "0",
      "amount": 0
    }
  },
  {
    "account": {
      "accountCode": 12330
    },
    "amountUnit": 1000,
    "debit": {
      "formatted": "0",
      "amount": 0
    },
    "credit": {
      "formatted": "0",
      "amount": 0
    }
  },
  {
    "account": {
      "accountCode": 12335
    },
    "amountUnit": 1000,
    "debit": {
      "formatted": "26,332,798",
      "amount": 26332797790
    },
    "credit": {
      "formatted": "0",
      "amount": 0
    }
  },
  {
    "account": {
      "accountCode": 12345
    },
    "amountUnit": 1000,
    "debit": {
      "formatted": "1,749,839",
      "amount": 1749838510
    },
    "credit": {
      "formatted": "0",
      "amount": 0
    }
  },
  {
    "account": {
      "accountCode": 12350
    },
    "amountUnit": 1000,
    "debit": {
      "formatted": "6,268,209",
      "amount": 6268209320
    },
    "credit": {
      "formatted": "0",
      "amount": 0
    }
  },
  {
    "account": {
      "accountCode": 12352
    },
    "amountUnit": 1000,
    "debit": {
      "formatted": "121,097",
      "amount": 121096500
    },
    "credit": {
      "formatted": "0",
      "amount": 0
    }
  },
  {
    "account": {
      "accountCode": 12355
    },
    "amountUnit": 1000,
    "debit": {
      "formatted": "484,107",
      "amount": 484107120
    },
    "credit": {
      "formatted": "0",
      "amount": 0
    }
  },
  {
    "account": {
      "accountCode": 12356
    },
    "amountUnit": 1000,
    "debit": {
      "formatted": "737,963",
      "amount": 737963400
    },
    "credit": {
      "formatted": "0",
      "amount": 0
    }
  },
  {
    "account": {
      "accountCode": 12360
    },
    "amountUnit": 1000,
    "debit": {
      "formatted": "0",
      "amount": 0
    },
    "credit": {
      "formatted": "0",
      "amount": 0
    }
  },
  {
    "account": {
      "accountCode": 12374
    },
    "amountUnit": 1000,
    "debit": {
      "formatted": "0",
      "amount": 0
    },
    "credit": {
      "formatted": "16,044",
      "amount": 16043760
    }
  },
  {
    "account": {
      "accountCode": 12375
    },
    "amountUnit": 1000,
    "debit": {
      "formatted": "2,134,303",
      "amount": 2134303279.9999998
    },
    "credit": {
      "formatted": "0",
      "amount": 0
    }
  },
  {
    "account": {
      "accountCode": 12410
    },
    "amountUnit": 1000,
    "debit": {
      "formatted": "0",
      "amount": 0
    },
    "credit": {
      "formatted": "0",
      "amount": 0
    }
  },
  {
    "account": {
      "accountCode": 12415
    },
    "amountUnit": 1000,
    "debit": {
      "formatted": "0",
      "amount": 0
    },
    "credit": {
      "formatted": "0",
      "amount": 0
    }
  },
  {
    "account": {
      "accountCode": 12420
    },
    "amountUnit": 1000,
    "debit": {
      "formatted": "3,694,637",
      "amount": 3694636740
    },
    "credit": {
      "formatted": "0",
      "amount": 0
    }
  },
  {
    "account": {
      "accountCode": 12425
    },
    "amountUnit": 1000,
    "debit": {
      "formatted": "5,455,780",
      "amount": 5455779530
    },
    "credit": {
      "formatted": "0",
      "amount": 0
    }
  },
  {
    "account": {
      "accountCode": 12427
    },
    "amountUnit": 1000,
    "debit": {
      "formatted": "0",
      "amount": 0
    },
    "credit": {
      "formatted": "0",
      "amount": 0
    }
  },
  {
    "account": {
      "accountCode": 12428
    },
    "amountUnit": 1000,
    "debit": {
      "formatted": "0",
      "amount": 0
    },
    "credit": {
      "formatted": "0",
      "amount": 0
    }
  },
  {
    "account": {
      "accountCode": 12430
    },
    "amountUnit": 1000,
    "debit": {
      "formatted": "0",
      "amount": 0
    },
    "credit": {
      "formatted": "0",
      "amount": 0
    }
  },
  {
    "account": {
      "accountCode": 12435
    },
    "amountUnit": 1000,
    "debit": {
      "formatted": "4,893,803",
      "amount": 4893802880
    },
    "credit": {
      "formatted": "0",
      "amount": 0
    }
  },
  {
    "account": {
      "accountCode": 12440
    },
    "amountUnit": 1000,
    "debit": {
      "formatted": "0",
      "amount": 0
    },
    "credit": {
      "formatted": "0",
      "amount": 0
    }
  },
  {
    "account": {
      "accountCode": 12445
    },
    "amountUnit": 1000,
    "debit": {
      "formatted": "0",
      "amount": 0
    },
    "credit": {
      "formatted": "0",
      "amount": 0
    }
  },
  {
    "account": {
      "accountCode": 12450
    },
    "amountUnit": 1000,
    "debit": {
      "formatted": "1,898,719",
      "amount": 1898718750
    },
    "credit": {
      "formatted": "0",
      "amount": 0
    }
  },
  {
    "account": {
      "accountCode": 12460
    },
    "amountUnit": 1000,
    "debit": {
      "formatted": "0",
      "amount": 0
    },
    "credit": {
      "formatted": "0",
      "amount": 0
    }
  },
  {
    "account": {
      "accountCode": 12465
    },
    "amountUnit": 1000,
    "debit": {
      "formatted": "0",
      "amount": 0
    },
    "credit": {
      "formatted": "0",
      "amount": 0
    }
  },
  {
    "account": {
      "accountCode": 12475
    },
    "amountUnit": 1000,
    "debit": {
      "formatted": "547,344",
      "amount": 547344290
    },
    "credit": {
      "formatted": "0",
      "amount": 0
    }
  },
  {
    "account": {
      "accountCode": 12510
    },
    "amountUnit": 1000,
    "debit": {
      "formatted": "281,637,840",
      "amount": 281637839500
    },
    "credit": {
      "formatted": "0",
      "amount": 0
    }
  },
  {
    "account": {
      "accountCode": 12515
    },
    "amountUnit": 1000,
    "debit": {
      "formatted": "80,275,483",
      "amount": 80275482640
    },
    "credit": {
      "formatted": "0",
      "amount": 0
    }
  },
  {
    "account": {
      "accountCode": 12516
    },
    "amountUnit": 1000,
    "debit": {
      "formatted": "0",
      "amount": 0
    },
    "credit": {
      "formatted": "0",
      "amount": 0
    }
  },
  {
    "account": {
      "accountCode": 12518
    },
    "amountUnit": 1000,
    "debit": {
      "formatted": "254,026",
      "amount": 254026130
    },
    "credit": {
      "formatted": "0",
      "amount": 0
    }
  },
  {
    "account": {
      "accountCode": 12519
    },
    "amountUnit": 1000,
    "debit": {
      "formatted": "0",
      "amount": 0
    },
    "credit": {
      "formatted": "0",
      "amount": 0
    }
  },
  {
    "account": {
      "accountCode": 12520
    },
    "amountUnit": 1000,
    "debit": {
      "formatted": "179,788",
      "amount": 179787760
    },
    "credit": {
      "formatted": "0",
      "amount": 0
    }
  },
  {
    "account": {
      "accountCode": 12525
    },
    "amountUnit": 1000,
    "debit": {
      "formatted": "0",
      "amount": 0
    },
    "credit": {
      "formatted": "0",
      "amount": 0
    }
  },
  {
    "account": {
      "accountCode": 12526
    },
    "amountUnit": 1000,
    "debit": {
      "formatted": "0",
      "amount": 0
    },
    "credit": {
      "formatted": "0",
      "amount": 0
    }
  },
  {
    "account": {
      "accountCode": 12527
    },
    "amountUnit": 1000,
    "debit": {
      "formatted": "0",
      "amount": 0
    },
    "credit": {
      "formatted": "0",
      "amount": 0
    }
  },
  {
    "account": {
      "accountCode": 12528
    },
    "amountUnit": 1000,
    "debit": {
      "formatted": "0",
      "amount": 0
    },
    "credit": {
      "formatted": "207,225,412",
      "amount": 207225411640
    }
  },
  {
    "account": {
      "accountCode": 12529
    },
    "amountUnit": 1000,
    "debit": {
      "formatted": "0",
      "amount": 0
    },
    "credit": {
      "formatted": "60,079,698",
      "amount": 60079697690
    }
  },
  {
    "account": {
      "accountCode": 12535
    },
    "amountUnit": 1000,
    "debit": {
      "formatted": "0",
      "amount": 0
    },
    "credit": {
      "formatted": "89,894",
      "amount": 89893730
    }
  },
  {
    "account": {
      "accountCode": 12565
    },
    "amountUnit": 1000,
    "debit": {
      "formatted": "0",
      "amount": 0
    },
    "credit": {
      "formatted": "0",
      "amount": 0
    }
  },
  {
    "account": {
      "accountCode": 12566
    },
    "amountUnit": 1000,
    "debit": {
      "formatted": "0",
      "amount": 0
    },
    "credit": {
      "formatted": "0",
      "amount": 0
    }
  },
  {
    "account": {
      "accountCode": 12574
    },
    "amountUnit": 1000,
    "debit": {
      "formatted": "0",
      "amount": 0
    },
    "credit": {
      "formatted": "75,403",
      "amount": 75402650
    }
  },
  {
    "account": {
      "accountCode": 12575
    },
    "amountUnit": 1000,
    "debit": {
      "formatted": "2,248,624",
      "amount": 2248623560
    },
    "credit": {
      "formatted": "0",
      "amount": 0
    }
  },
  {
    "account": {
      "accountCode": 12590
    },
    "amountUnit": 1000,
    "debit": {
      "formatted": "0",
      "amount": 0
    },
    "credit": {
      "formatted": "6,961,983",
      "amount": 6961982600
    }
  },
  {
    "account": {
      "accountCode": 12610
    },
    "amountUnit": 1000,
    "debit": {
      "formatted": "44,286",
      "amount": 44286000
    },
    "credit": {
      "formatted": "0",
      "amount": 0
    }
  },
  {
    "account": {
      "accountCode": 12615
    },
    "amountUnit": 1000,
    "debit": {
      "formatted": "7,287,154",
      "amount": 7287154250
    },
    "credit": {
      "formatted": "0",
      "amount": 0
    }
  },
  {
    "account": {
      "accountCode": 12620
    },
    "amountUnit": 1000,
    "debit": {
      "formatted": "711,397",
      "amount": 711396910
    },
    "credit": {
      "formatted": "0",
      "amount": 0
    }
  },
  {
    "account": {
      "accountCode": 12621
    },
    "amountUnit": 1000,
    "debit": {
      "formatted": "0",
      "amount": 0
    },
    "credit": {
      "formatted": "711,397",
      "amount": 711396910
    }
  },
  {
    "account": {
      "accountCode": 12640
    },
    "amountUnit": 1000,
    "debit": {
      "formatted": "0",
      "amount": 0
    },
    "credit": {
      "formatted": "0",
      "amount": 0
    }
  },
  {
    "account": {
      "accountCode": 12645
    },
    "amountUnit": 1000,
    "debit": {
      "formatted": "2,714,416",
      "amount": 2714416000
    },
    "credit": {
      "formatted": "0",
      "amount": 0
    }
  },
  {
    "account": {
      "accountCode": 12646
    },
    "amountUnit": 1000,
    "debit": {
      "formatted": "0",
      "amount": 0
    },
    "credit": {
      "formatted": "2,714,416",
      "amount": 2714416000
    }
  },
  {
    "account": {
      "accountCode": 12650
    },
    "amountUnit": 1000,
    "debit": {
      "formatted": "0",
      "amount": 0
    },
    "credit": {
      "formatted": "0",
      "amount": 0
    }
  },
  {
    "account": {
      "accountCode": 12651
    },
    "amountUnit": 1000,
    "debit": {
      "formatted": "0",
      "amount": 0
    },
    "credit": {
      "formatted": "0",
      "amount": 0
    }
  },
  {
    "account": {
      "accountCode": 12655
    },
    "amountUnit": 1000,
    "debit": {
      "formatted": "0",
      "amount": 0
    },
    "credit": {
      "formatted": "0",
      "amount": 0
    }
  },
  {
    "account": {
      "accountCode": 12656
    },
    "amountUnit": 1000,
    "debit": {
      "formatted": "0",
      "amount": 0
    },
    "credit": {
      "formatted": "0",
      "amount": 0
    }
  },
  {
    "account": {
      "accountCode": 12670
    },
    "amountUnit": 1000,
    "debit": {
      "formatted": "0",
      "amount": 0
    },
    "credit": {
      "formatted": "0",
      "amount": 0
    }
  },
  {
    "account": {
      "accountCode": 12675
    },
    "amountUnit": 1000,
    "debit": {
      "formatted": "1,740,181",
      "amount": 1740180910
    },
    "credit": {
      "formatted": "0",
      "amount": 0
    }
  },
  {
    "account": {
      "accountCode": 12710
    },
    "amountUnit": 1000,
    "debit": {
      "formatted": "76,695",
      "amount": 76695010
    },
    "credit": {
      "formatted": "0",
      "amount": 0
    }
  },
  {
    "account": {
      "accountCode": 12720
    },
    "amountUnit": 1000,
    "debit": {
      "formatted": "0",
      "amount": 0
    },
    "credit": {
      "formatted": "2,050,498",
      "amount": 2050498460
    }
  },
  {
    "account": {
      "accountCode": 12725
    },
    "amountUnit": 1000,
    "debit": {
      "formatted": "19,144",
      "amount": 19144320
    },
    "credit": {
      "formatted": "0",
      "amount": 0
    }
  },
  {
    "account": {
      "accountCode": 12730
    },
    "amountUnit": 1000,
    "debit": {
      "formatted": "958,577",
      "amount": 958576510
    },
    "credit": {
      "formatted": "0",
      "amount": 0
    }
  },
  {
    "account": {
      "accountCode": 12740
    },
    "amountUnit": 1000,
    "debit": {
      "formatted": "166,127",
      "amount": 166126950
    },
    "credit": {
      "formatted": "0",
      "amount": 0
    }
  },
  {
    "account": {
      "accountCode": 12745
    },
    "amountUnit": 1000,
    "debit": {
      "formatted": "47,550",
      "amount": 47549890
    },
    "credit": {
      "formatted": "0",
      "amount": 0
    }
  },
  {
    "account": {
      "accountCode": 12750
    },
    "amountUnit": 1000,
    "debit": {
      "formatted": "1,285,013",
      "amount": 1285013100
    },
    "credit": {
      "formatted": "0",
      "amount": 0
    }
  },
  {
    "account": {
      "accountCode": 12785
    },
    "amountUnit": 1000,
    "debit": {
      "formatted": "0",
      "amount": 0
    },
    "credit": {
      "formatted": "750",
      "amount": 750000
    }
  },
  {
    "account": {
      "accountCode": 12820
    },
    "amountUnit": 1000,
    "debit": {
      "formatted": "0",
      "amount": 0
    },
    "credit": {
      "formatted": "14,666,824",
      "amount": 14666824210
    }
  },
  {
    "account": {
      "accountCode": 12830
    },
    "amountUnit": 1000,
    "debit": {
      "formatted": "0",
      "amount": 0
    },
    "credit": {
      "formatted": "706,935",
      "amount": 706935070
    }
  },
  {
    "account": {
      "accountCode": 12860
    },
    "amountUnit": 1000,
    "debit": {
      "formatted": "4,215,581",
      "amount": 4215581429.9999995
    },
    "credit": {
      "formatted": "0",
      "amount": 0
    }
  },
  {
    "account": {
      "accountCode": 12880
    },
    "amountUnit": 1000,
    "debit": {
      "formatted": "0",
      "amount": 0
    },
    "credit": {
      "formatted": "818,838",
      "amount": 818837530
    }
  },
  {
    "account": {
      "accountCode": 13110
    },
    "amountUnit": 1000,
    "debit": {
      "formatted": "1,083,788",
      "amount": 1083788120
    },
    "credit": {
      "formatted": "0",
      "amount": 0
    }
  },
  {
    "account": {
      "accountCode": 13120
    },
    "amountUnit": 1000,
    "debit": {
      "formatted": "0",
      "amount": 0
    },
    "credit": {
      "formatted": "858,755",
      "amount": 858754780
    }
  },
  {
    "account": {
      "accountCode": 13130
    },
    "amountUnit": 1000,
    "debit": {
      "formatted": "612,665",
      "amount": 612664770
    },
    "credit": {
      "formatted": "0",
      "amount": 0
    }
  },
  {
    "account": {
      "accountCode": 13140
    },
    "amountUnit": 1000,
    "debit": {
      "formatted": "0",
      "amount": 0
    },
    "credit": {
      "formatted": "482,285",
      "amount": 482284640
    }
  },
  {
    "account": {
      "accountCode": 13150
    },
    "amountUnit": 1000,
    "debit": {
      "formatted": "1,299,981",
      "amount": 1299980810
    },
    "credit": {
      "formatted": "0",
      "amount": 0
    }
  },
  {
    "account": {
      "accountCode": 13170
    },
    "amountUnit": 1000,
    "debit": {
      "formatted": "0",
      "amount": 0
    },
    "credit": {
      "formatted": "888,753",
      "amount": 888752770
    }
  },
  {
    "account": {
      "accountCode": 13180
    },
    "amountUnit": 1000,
    "debit": {
      "formatted": "903,138",
      "amount": 903138220
    },
    "credit": {
      "formatted": "0",
      "amount": 0
    }
  },
  {
    "account": {
      "accountCode": 13185
    },
    "amountUnit": 1000,
    "debit": {
      "formatted": "0",
      "amount": 0
    },
    "credit": {
      "formatted": "681,413",
      "amount": 681413030
    }
  },
  {
    "account": {
      "accountCode": 13190
    },
    "amountUnit": 1000,
    "debit": {
      "formatted": "0",
      "amount": 0
    },
    "credit": {
      "formatted": "0",
      "amount": 0
    }
  },
  {
    "account": {
      "accountCode": 13195
    },
    "amountUnit": 1000,
    "debit": {
      "formatted": "0",
      "amount": 0
    },
    "credit": {
      "formatted": "0",
      "amount": 0
    }
  },
  {
    "account": {
      "accountCode": 13210
    },
    "amountUnit": 1000,
    "debit": {
      "formatted": "4,094,731",
      "amount": 4094731010
    },
    "credit": {
      "formatted": "0",
      "amount": 0
    }
  },
  {
    "account": {
      "accountCode": 13220
    },
    "amountUnit": 1000,
    "debit": {
      "formatted": "0",
      "amount": 0
    },
    "credit": {
      "formatted": "3,052,805",
      "amount": 3052805350
    }
  },
  {
    "account": {
      "accountCode": 14105
    },
    "amountUnit": 1000,
    "debit": {
      "formatted": "0",
      "amount": 0
    },
    "credit": {
      "formatted": "0",
      "amount": 0
    }
  },
  {
    "account": {
      "accountCode": 14106
    },
    "amountUnit": 1000,
    "debit": {
      "formatted": "0",
      "amount": 0
    },
    "credit": {
      "formatted": "0",
      "amount": 0
    }
  },
  {
    "account": {
      "accountCode": 14110
    },
    "amountUnit": 1000,
    "debit": {
      "formatted": "0",
      "amount": 0
    },
    "credit": {
      "formatted": "0",
      "amount": 0
    }
  },
  {
    "account": {
      "accountCode": 14115
    },
    "amountUnit": 1000,
    "debit": {
      "formatted": "12,327",
      "amount": 12327260
    },
    "credit": {
      "formatted": "0",
      "amount": 0
    }
  },
  {
    "account": {
      "accountCode": 14117
    },
    "amountUnit": 1000,
    "debit": {
      "formatted": "3,750",
      "amount": 3750000
    },
    "credit": {
      "formatted": "0",
      "amount": 0
    }
  },
  {
    "account": {
      "accountCode": 14120
    },
    "amountUnit": 1000,
    "debit": {
      "formatted": "21,246",
      "amount": 21246390
    },
    "credit": {
      "formatted": "0",
      "amount": 0
    }
  },
  {
    "account": {
      "accountCode": 14125
    },
    "amountUnit": 1000,
    "debit": {
      "formatted": "10,311",
      "amount": 10311210
    },
    "credit": {
      "formatted": "0",
      "amount": 0
    }
  },
  {
    "account": {
      "accountCode": 14130
    },
    "amountUnit": 1000,
    "debit": {
      "formatted": "16,311",
      "amount": 16310720
    },
    "credit": {
      "formatted": "0",
      "amount": 0
    }
  },
  {
    "account": {
      "accountCode": 14135
    },
    "amountUnit": 1000,
    "debit": {
      "formatted": "0",
      "amount": 0
    },
    "credit": {
      "formatted": "0",
      "amount": 0
    }
  },
  {
    "account": {
      "accountCode": 14140
    },
    "amountUnit": 1000,
    "debit": {
      "formatted": "0",
      "amount": 0
    },
    "credit": {
      "formatted": "0",
      "amount": 0
    }
  },
  {
    "account": {
      "accountCode": 14150
    },
    "amountUnit": 1000,
    "debit": {
      "formatted": "0",
      "amount": 0
    },
    "credit": {
      "formatted": "0",
      "amount": 0
    }
  },
  {
    "account": {
      "accountCode": 14210
    },
    "amountUnit": 1000,
    "debit": {
      "formatted": "117,514",
      "amount": 117514420
    },
    "credit": {
      "formatted": "0",
      "amount": 0
    }
  },
  {
    "account": {
      "accountCode": 14215
    },
    "amountUnit": 1000,
    "debit": {
      "formatted": "1,387",
      "amount": 1386960
    },
    "credit": {
      "formatted": "0",
      "amount": 0
    }
  },
  {
    "account": {
      "accountCode": 14217
    },
    "amountUnit": 1000,
    "debit": {
      "formatted": "332,835",
      "amount": 332835160
    },
    "credit": {
      "formatted": "0",
      "amount": 0
    }
  },
  {
    "account": {
      "accountCode": 14220
    },
    "amountUnit": 1000,
    "debit": {
      "formatted": "777,492",
      "amount": 777491510
    },
    "credit": {
      "formatted": "0",
      "amount": 0
    }
  },
  {
    "account": {
      "accountCode": 14225
    },
    "amountUnit": 1000,
    "debit": {
      "formatted": "116,025",
      "amount": 116024790
    },
    "credit": {
      "formatted": "0",
      "amount": 0
    }
  },
  {
    "account": {
      "accountCode": 14230
    },
    "amountUnit": 1000,
    "debit": {
      "formatted": "27,852",
      "amount": 27852010
    },
    "credit": {
      "formatted": "0",
      "amount": 0
    }
  },
  {
    "account": {
      "accountCode": 14235
    },
    "amountUnit": 1000,
    "debit": {
      "formatted": "281,019",
      "amount": 281019330
    },
    "credit": {
      "formatted": "0",
      "amount": 0
    }
  },
  {
    "account": {
      "accountCode": 14236
    },
    "amountUnit": 1000,
    "debit": {
      "formatted": "0",
      "amount": 0
    },
    "credit": {
      "formatted": "0",
      "amount": 0
    }
  },
  {
    "account": {
      "accountCode": 14240
    },
    "amountUnit": 1000,
    "debit": {
      "formatted": "19,291",
      "amount": 19291190
    },
    "credit": {
      "formatted": "0",
      "amount": 0
    }
  },
  {
    "account": {
      "accountCode": 14290
    },
    "amountUnit": 1000,
    "debit": {
      "formatted": "2,011",
      "amount": 2010750
    },
    "credit": {
      "formatted": "0",
      "amount": 0
    }
  },
  {
    "account": {
      "accountCode": 15000
    },
    "amountUnit": 1000,
    "debit": {
      "formatted": "0",
      "amount": 0
    },
    "credit": {
      "formatted": "0",
      "amount": 0
    }
  },
  {
    "account": {
      "accountCode": 15010
    },
    "amountUnit": 1000,
    "debit": {
      "formatted": "0",
      "amount": 0
    },
    "credit": {
      "formatted": "0",
      "amount": 0
    }
  },
  {
    "account": {
      "accountCode": 15020
    },
    "amountUnit": 1000,
    "debit": {
      "formatted": "0",
      "amount": 0
    },
    "credit": {
      "formatted": "0",
      "amount": 0
    }
  },
  {
    "account": {
      "accountCode": 15030
    },
    "amountUnit": 1000,
    "debit": {
      "formatted": "0",
      "amount": 0
    },
    "credit": {
      "formatted": "0",
      "amount": 0
    }
  },
  {
    "account": {
      "accountCode": 17000
    },
    "amountUnit": 1000,
    "debit": {
      "formatted": "31,275",
      "amount": 31275440
    },
    "credit": {
      "formatted": "0",
      "amount": 0
    }
  },
  {
    "account": {
      "accountCode": 17010
    },
    "amountUnit": 1000,
    "debit": {
      "formatted": "4,535",
      "amount": 4534990
    },
    "credit": {
      "formatted": "0",
      "amount": 0
    }
  },
  {
    "account": {
      "accountCode": 17020
    },
    "amountUnit": 1000,
    "debit": {
      "formatted": "0",
      "amount": 0
    },
    "credit": {
      "formatted": "0",
      "amount": 0
    }
  },
  {
    "account": {
      "accountCode": 17030
    },
    "amountUnit": 1000,
    "debit": {
      "formatted": "68,662",
      "amount": 68661830
    },
    "credit": {
      "formatted": "0",
      "amount": 0
    }
  },
  {
    "account": {
      "accountCode": 17040
    },
    "amountUnit": 1000,
    "debit": {
      "formatted": "141,649",
      "amount": 141648820
    },
    "credit": {
      "formatted": "0",
      "amount": 0
    }
  },
  {
    "account": {
      "accountCode": 17050
    },
    "amountUnit": 1000,
    "debit": {
      "formatted": "717,150",
      "amount": 717149890
    },
    "credit": {
      "formatted": "0",
      "amount": 0
    }
  },
  {
    "account": {
      "accountCode": 17055
    },
    "amountUnit": 1000,
    "debit": {
      "formatted": "189,329",
      "amount": 189329010
    },
    "credit": {
      "formatted": "0",
      "amount": 0
    }
  },
  {
    "account": {
      "accountCode": 17060
    },
    "amountUnit": 1000,
    "debit": {
      "formatted": "38,582",
      "amount": 38581590
    },
    "credit": {
      "formatted": "0",
      "amount": 0
    }
  },
  {
    "account": {
      "accountCode": 17085
    },
    "amountUnit": 1000,
    "debit": {
      "formatted": "56,537",
      "amount": 56536880
    },
    "credit": {
      "formatted": "0",
      "amount": 0
    }
  },
  {
    "account": {
      "accountCode": 17086
    },
    "amountUnit": 1000,
    "debit": {
      "formatted": "0",
      "amount": 0
    },
    "credit": {
      "formatted": "0",
      "amount": 0
    }
  },
  {
    "account": {
      "accountCode": 17090
    },
    "amountUnit": 1000,
    "debit": {
      "formatted": "121,431",
      "amount": 121430920
    },
    "credit": {
      "formatted": "0",
      "amount": 0
    }
  },
  {
    "account": {
      "accountCode": 17105
    },
    "amountUnit": 1000,
    "debit": {
      "formatted": "0",
      "amount": 0
    },
    "credit": {
      "formatted": "0",
      "amount": 0
    }
  },
  {
    "account": {
      "accountCode": 17110
    },
    "amountUnit": 1000,
    "debit": {
      "formatted": "187,682",
      "amount": 187682300
    },
    "credit": {
      "formatted": "0",
      "amount": 0
    }
  },
  {
    "account": {
      "accountCode": 17120
    },
    "amountUnit": 1000,
    "debit": {
      "formatted": "100",
      "amount": 100000
    },
    "credit": {
      "formatted": "0",
      "amount": 0
    }
  },
  {
    "account": {
      "accountCode": 17129
    },
    "amountUnit": 1000,
    "debit": {
      "formatted": "484,057",
      "amount": 484056710
    },
    "credit": {
      "formatted": "0",
      "amount": 0
    }
  },
  {
    "account": {
      "accountCode": 17130
    },
    "amountUnit": 1000,
    "debit": {
      "formatted": "219",
      "amount": 219370
    },
    "credit": {
      "formatted": "0",
      "amount": 0
    }
  },
  {
    "account": {
      "accountCode": 17131
    },
    "amountUnit": 1000,
    "debit": {
      "formatted": "0",
      "amount": 0
    },
    "credit": {
      "formatted": "0",
      "amount": 0
    }
  },
  {
    "account": {
      "accountCode": 17132
    },
    "amountUnit": 1000,
    "debit": {
      "formatted": "39,911",
      "amount": 39911350
    },
    "credit": {
      "formatted": "0",
      "amount": 0
    }
  },
  {
    "account": {
      "accountCode": 17133
    },
    "amountUnit": 1000,
    "debit": {
      "formatted": "1,250",
      "amount": 1250000
    },
    "credit": {
      "formatted": "0",
      "amount": 0
    }
  },
  {
    "account": {
      "accountCode": 17134
    },
    "amountUnit": 1000,
    "debit": {
      "formatted": "0",
      "amount": 0
    },
    "credit": {
      "formatted": "0",
      "amount": 0
    }
  },
  {
    "account": {
      "accountCode": 17135
    },
    "amountUnit": 1000,
    "debit": {
      "formatted": "0",
      "amount": 0
    },
    "credit": {
      "formatted": "0",
      "amount": 0
    }
  },
  {
    "account": {
      "accountCode": 17136
    },
    "amountUnit": 1000,
    "debit": {
      "formatted": "0",
      "amount": 0
    },
    "credit": {
      "formatted": "0",
      "amount": 0
    }
  },
  {
    "account": {
      "accountCode": 17140
    },
    "amountUnit": 1000,
    "debit": {
      "formatted": "0",
      "amount": 0
    },
    "credit": {
      "formatted": "0",
      "amount": 0
    }
  },
  {
    "account": {
      "accountCode": 17150
    },
    "amountUnit": 1000,
    "debit": {
      "formatted": "0",
      "amount": 0
    },
    "credit": {
      "formatted": "0",
      "amount": 0
    }
  },
  {
    "account": {
      "accountCode": 17155
    },
    "amountUnit": 1000,
    "debit": {
      "formatted": "0",
      "amount": 0
    },
    "credit": {
      "formatted": "0",
      "amount": 0
    }
  },
  {
    "account": {
      "accountCode": 17160
    },
    "amountUnit": 1000,
    "debit": {
      "formatted": "0",
      "amount": 0
    },
    "credit": {
      "formatted": "0",
      "amount": 0
    }
  },
  {
    "account": {
      "accountCode": 17165
    },
    "amountUnit": 1000,
    "debit": {
      "formatted": "0",
      "amount": 0
    },
    "credit": {
      "formatted": "0",
      "amount": 0
    }
  },
  {
    "account": {
      "accountCode": 17170
    },
    "amountUnit": 1000,
    "debit": {
      "formatted": "0",
      "amount": 0
    },
    "credit": {
      "formatted": "0",
      "amount": 0
    }
  },
  {
    "account": {
      "accountCode": 17180
    },
    "amountUnit": 1000,
    "debit": {
      "formatted": "6,963",
      "amount": 6962820
    },
    "credit": {
      "formatted": "0",
      "amount": 0
    }
  },
  {
    "account": {
      "accountCode": 17190
    },
    "amountUnit": 1000,
    "debit": {
      "formatted": "3,000,200",
      "amount": 3000200000
    },
    "credit": {
      "formatted": "0",
      "amount": 0
    }
  },
  {
    "account": {
      "accountCode": 17191
    },
    "amountUnit": 1000,
    "debit": {
      "formatted": "170,000",
      "amount": 170000000
    },
    "credit": {
      "formatted": "0",
      "amount": 0
    }
  },
  {
    "account": {
      "accountCode": 17197
    },
    "amountUnit": 1000,
    "debit": {
      "formatted": "0",
      "amount": 0
    },
    "credit": {
      "formatted": "0",
      "amount": 0
    }
  },
  {
    "account": {
      "accountCode": 17198
    },
    "amountUnit": 1000,
    "debit": {
      "formatted": "0",
      "amount": 0
    },
    "credit": {
      "formatted": "0",
      "amount": 0
    }
  },
  {
    "account": {
      "accountCode": 17220
    },
    "amountUnit": 1000,
    "debit": {
      "formatted": "54,019",
      "amount": 54019110
    },
    "credit": {
      "formatted": "0",
      "amount": 0
    }
  },
  {
    "account": {
      "accountCode": 17230
    },
    "amountUnit": 1000,
    "debit": {
      "formatted": "0",
      "amount": 0
    },
    "credit": {
      "formatted": "0",
      "amount": 0
    }
  },
  {
    "account": {
      "accountCode": 17240
    },
    "amountUnit": 1000,
    "debit": {
      "formatted": "0",
      "amount": 0
    },
    "credit": {
      "formatted": "0",
      "amount": 0
    }
  },
  {
    "account": {
      "accountCode": 17320
    },
    "amountUnit": 1000,
    "debit": {
      "formatted": "0",
      "amount": 0
    },
    "credit": {
      "formatted": "0",
      "amount": 0
    }
  },
  {
    "account": {
      "accountCode": 17325
    },
    "amountUnit": 1000,
    "debit": {
      "formatted": "0",
      "amount": 0
    },
    "credit": {
      "formatted": "0",
      "amount": 0
    }
  },
  {
    "account": {
      "accountCode": 17350
    },
    "amountUnit": 1000,
    "debit": {
      "formatted": "0",
      "amount": 0
    },
    "credit": {
      "formatted": "0",
      "amount": 0
    }
  },
  {
    "account": {
      "accountCode": 17410
    },
    "amountUnit": 1000,
    "debit": {
      "formatted": "4,496,939",
      "amount": 4496939370
    },
    "credit": {
      "formatted": "0",
      "amount": 0
    }
  },
  {
    "account": {
      "accountCode": 17415
    },
    "amountUnit": 1000,
    "debit": {
      "formatted": "574,347",
      "amount": 574346540
    },
    "credit": {
      "formatted": "0",
      "amount": 0
    }
  },
  {
    "account": {
      "accountCode": 17420
    },
    "amountUnit": 1000,
    "debit": {
      "formatted": "721,534",
      "amount": 721533780
    },
    "credit": {
      "formatted": "0",
      "amount": 0
    }
  },
  {
    "account": {
      "accountCode": 17510
    },
    "amountUnit": 1000,
    "debit": {
      "formatted": "2,879,485",
      "amount": 2879484730
    },
    "credit": {
      "formatted": "0",
      "amount": 0
    }
  },
  {
    "account": {
      "accountCode": 17520
    },
    "amountUnit": 1000,
    "debit": {
      "formatted": "4,888,266",
      "amount": 4888266310
    },
    "credit": {
      "formatted": "0",
      "amount": 0
    }
  },
  {
    "account": {
      "accountCode": 17525
    },
    "amountUnit": 1000,
    "debit": {
      "formatted": "703,725",
      "amount": 703724720
    },
    "credit": {
      "formatted": "0",
      "amount": 0
    }
  },
  {
    "account": {
      "accountCode": 17530
    },
    "amountUnit": 1000,
    "debit": {
      "formatted": "0",
      "amount": 0
    },
    "credit": {
      "formatted": "0",
      "amount": 0
    }
  },
  {
    "account": {
      "accountCode": 17610
    },
    "amountUnit": 1000,
    "debit": {
      "formatted": "0",
      "amount": 0
    },
    "credit": {
      "formatted": "0",
      "amount": 0
    }
  },
  {
    "account": {
      "accountCode": 20010
    },
    "amountUnit": 1000,
    "debit": {
      "formatted": "0",
      "amount": 0
    },
    "credit": {
      "formatted": "149,290,210",
      "amount": 149290210380
    }
  },
  {
    "account": {
      "accountCode": 20015
    },
    "amountUnit": 1000,
    "debit": {
      "formatted": "0",
      "amount": 0
    },
    "credit": {
      "formatted": "76,695",
      "amount": 76695010
    }
  },
  {
    "account": {
      "accountCode": 20020
    },
    "amountUnit": 1000,
    "debit": {
      "formatted": "0",
      "amount": 0
    },
    "credit": {
      "formatted": "9,482",
      "amount": 9482380
    }
  },
  {
    "account": {
      "accountCode": 20025
    },
    "amountUnit": 1000,
    "debit": {
      "formatted": "0",
      "amount": 0
    },
    "credit": {
      "formatted": "5,751,152",
      "amount": 5751151710
    }
  },
  {
    "account": {
      "accountCode": 20030
    },
    "amountUnit": 1000,
    "debit": {
      "formatted": "0",
      "amount": 0
    },
    "credit": {
      "formatted": "125,058",
      "amount": 125058090
    }
  },
  {
    "account": {
      "accountCode": 20035
    },
    "amountUnit": 1000,
    "debit": {
      "formatted": "0",
      "amount": 0
    },
    "credit": {
      "formatted": "1,213",
      "amount": 1213000
    }
  },
  {
    "account": {
      "accountCode": 20040
    },
    "amountUnit": 1000,
    "debit": {
      "formatted": "0",
      "amount": 0
    },
    "credit": {
      "formatted": "0",
      "amount": 0
    }
  },
  {
    "account": {
      "accountCode": 20045
    },
    "amountUnit": 1000,
    "debit": {
      "formatted": "0",
      "amount": 0
    },
    "credit": {
      "formatted": "0",
      "amount": 0
    }
  },
  {
    "account": {
      "accountCode": 20047
    },
    "amountUnit": 1000,
    "debit": {
      "formatted": "0",
      "amount": 0
    },
    "credit": {
      "formatted": "0",
      "amount": 0
    }
  },
  {
    "account": {
      "accountCode": 20050
    },
    "amountUnit": 1000,
    "debit": {
      "formatted": "0",
      "amount": 0
    },
    "credit": {
      "formatted": "0",
      "amount": 0
    }
  },
  {
    "account": {
      "accountCode": 20060
    },
    "amountUnit": 1000,
    "debit": {
      "formatted": "0",
      "amount": 0
    },
    "credit": {
      "formatted": "610,378",
      "amount": 610378490
    }
  },
  {
    "account": {
      "accountCode": 20061
    },
    "amountUnit": 1000,
    "debit": {
      "formatted": "0",
      "amount": 0
    },
    "credit": {
      "formatted": "0",
      "amount": 0
    }
  },
  {
    "account": {
      "accountCode": 20062
    },
    "amountUnit": 1000,
    "debit": {
      "formatted": "0",
      "amount": 0
    },
    "credit": {
      "formatted": "0",
      "amount": 0
    }
  },
  {
    "account": {
      "accountCode": 20063
    },
    "amountUnit": 1000,
    "debit": {
      "formatted": "0",
      "amount": 0
    },
    "credit": {
      "formatted": "821,971",
      "amount": 821970990
    }
  },
  {
    "account": {
      "accountCode": 20064
    },
    "amountUnit": 1000,
    "debit": {
      "formatted": "0",
      "amount": 0
    },
    "credit": {
      "formatted": "87,930",
      "amount": 87929520
    }
  },
  {
    "account": {
      "accountCode": 20065
    },
    "amountUnit": 1000,
    "debit": {
      "formatted": "0",
      "amount": 0
    },
    "credit": {
      "formatted": "43,125",
      "amount": 43124940
    }
  },
  {
    "account": {
      "accountCode": 20066
    },
    "amountUnit": 1000,
    "debit": {
      "formatted": "0",
      "amount": 0
    },
    "credit": {
      "formatted": "0",
      "amount": 0
    }
  },
  {
    "account": {
      "accountCode": 20067
    },
    "amountUnit": 1000,
    "debit": {
      "formatted": "0",
      "amount": 0
    },
    "credit": {
      "formatted": "7,540",
      "amount": 7539500
    }
  },
  {
    "account": {
      "accountCode": 20068
    },
    "amountUnit": 1000,
    "debit": {
      "formatted": "0",
      "amount": 0
    },
    "credit": {
      "formatted": "0",
      "amount": 0
    }
  },
  {
    "account": {
      "accountCode": 20069
    },
    "amountUnit": 1000,
    "debit": {
      "formatted": "0",
      "amount": 0
    },
    "credit": {
      "formatted": "0",
      "amount": 0
    }
  },
  {
    "account": {
      "accountCode": 20070
    },
    "amountUnit": 1000,
    "debit": {
      "formatted": "0",
      "amount": 0
    },
    "credit": {
      "formatted": "0",
      "amount": 0
    }
  },
  {
    "account": {
      "accountCode": 20071
    },
    "amountUnit": 1000,
    "debit": {
      "formatted": "0",
      "amount": 0
    },
    "credit": {
      "formatted": "193,924",
      "amount": 193924390
    }
  },
  {
    "account": {
      "accountCode": 20072
    },
    "amountUnit": 1000,
    "debit": {
      "formatted": "0",
      "amount": 0
    },
    "credit": {
      "formatted": "18,250",
      "amount": 18250000
    }
  },
  {
    "account": {
      "accountCode": 20073
    },
    "amountUnit": 1000,
    "debit": {
      "formatted": "0",
      "amount": 0
    },
    "credit": {
      "formatted": "0",
      "amount": 0
    }
  },
  {
    "account": {
      "accountCode": 20074
    },
    "amountUnit": 1000,
    "debit": {
      "formatted": "0",
      "amount": 0
    },
    "credit": {
      "formatted": "73,320",
      "amount": 73320200
    }
  },
  {
    "account": {
      "accountCode": 20075
    },
    "amountUnit": 1000,
    "debit": {
      "formatted": "0",
      "amount": 0
    },
    "credit": {
      "formatted": "0",
      "amount": 0
    }
  },
  {
    "account": {
      "accountCode": 20076
    },
    "amountUnit": 1000,
    "debit": {
      "formatted": "0",
      "amount": 0
    },
    "credit": {
      "formatted": "55,644",
      "amount": 55644400
    }
  },
  {
    "account": {
      "accountCode": 20077
    },
    "amountUnit": 1000,
    "debit": {
      "formatted": "0",
      "amount": 0
    },
    "credit": {
      "formatted": "981",
      "amount": 981050
    }
  },
  {
    "account": {
      "accountCode": 20078
    },
    "amountUnit": 1000,
    "debit": {
      "formatted": "0",
      "amount": 0
    },
    "credit": {
      "formatted": "42,440",
      "amount": 42440000
    }
  },
  {
    "account": {
      "accountCode": 20079
    },
    "amountUnit": 1000,
    "debit": {
      "formatted": "0",
      "amount": 0
    },
    "credit": {
      "formatted": "399,629",
      "amount": 399628780
    }
  },
  {
    "account": {
      "accountCode": 20080
    },
    "amountUnit": 1000,
    "debit": {
      "formatted": "95,548",
      "amount": 95548400
    },
    "credit": {
      "formatted": "0",
      "amount": 0
    }
  },
  {
    "account": {
      "accountCode": 20081
    },
    "amountUnit": 1000,
    "debit": {
      "formatted": "0",
      "amount": 0
    },
    "credit": {
      "formatted": "0",
      "amount": 0
    }
  },
  {
    "account": {
      "accountCode": 20083
    },
    "amountUnit": 1000,
    "debit": {
      "formatted": "0",
      "amount": 0
    },
    "credit": {
      "formatted": "0",
      "amount": 0
    }
  },
  {
    "account": {
      "accountCode": 20085
    },
    "amountUnit": 1000,
    "debit": {
      "formatted": "8,640",
      "amount": 8639720
    },
    "credit": {
      "formatted": "0",
      "amount": 0
    }
  },
  {
    "account": {
      "accountCode": 20090
    },
    "amountUnit": 1000,
    "debit": {
      "formatted": "7,555",
      "amount": 7554620
    },
    "credit": {
      "formatted": "0",
      "amount": 0
    }
  },
  {
    "account": {
      "accountCode": 20091
    },
    "amountUnit": 1000,
    "debit": {
      "formatted": "77,402",
      "amount": 77402280
    },
    "credit": {
      "formatted": "0",
      "amount": 0
    }
  },
  {
    "account": {
      "accountCode": 20095
    },
    "amountUnit": 1000,
    "debit": {
      "formatted": "0",
      "amount": 0
    },
    "credit": {
      "formatted": "0",
      "amount": 0
    }
  },
  {
    "account": {
      "accountCode": 20097
    },
    "amountUnit": 1000,
    "debit": {
      "formatted": "0",
      "amount": 0
    },
    "credit": {
      "formatted": "0",
      "amount": 0
    }
  },
  {
    "account": {
      "accountCode": 20100
    },
    "amountUnit": 1000,
    "debit": {
      "formatted": "0",
      "amount": 0
    },
    "credit": {
      "formatted": "593,779",
      "amount": 593779170
    }
  },
  {
    "account": {
      "accountCode": 20150
    },
    "amountUnit": 1000,
    "debit": {
      "formatted": "0",
      "amount": 0
    },
    "credit": {
      "formatted": "5,076,146",
      "amount": 5076145620
    }
  },
  {
    "account": {
      "accountCode": 20209
    },
    "amountUnit": 1000,
    "debit": {
      "formatted": "0",
      "amount": 0
    },
    "credit": {
      "formatted": "0",
      "amount": 0
    }
  },
  {
    "account": {
      "accountCode": 20210
    },
    "amountUnit": 1000,
    "debit": {
      "formatted": "0",
      "amount": 0
    },
    "credit": {
      "formatted": "35,452,899",
      "amount": 35452899430
    }
  },
  {
    "account": {
      "accountCode": 20250
    },
    "amountUnit": 1000,
    "debit": {
      "formatted": "0",
      "amount": 0
    },
    "credit": {
      "formatted": "9,163,976",
      "amount": 9163976090
    }
  },
  {
    "account": {
      "accountCode": 20260
    },
    "amountUnit": 1000,
    "debit": {
      "formatted": "0",
      "amount": 0
    },
    "credit": {
      "formatted": "8,852,864",
      "amount": 8852864450
    }
  },
  {
    "account": {
      "accountCode": 20265
    },
    "amountUnit": 1000,
    "debit": {
      "formatted": "0",
      "amount": 0
    },
    "credit": {
      "formatted": "2,523,082",
      "amount": 2523081960
    }
  },
  {
    "account": {
      "accountCode": 20270
    },
    "amountUnit": 1000,
    "debit": {
      "formatted": "0",
      "amount": 0
    },
    "credit": {
      "formatted": "61,437,907",
      "amount": 61437906910
    }
  },
  {
    "account": {
      "accountCode": 20275
    },
    "amountUnit": 1000,
    "debit": {
      "formatted": "0",
      "amount": 0
    },
    "credit": {
      "formatted": "9,814,291",
      "amount": 9814290850
    }
  },
  {
    "account": {
      "accountCode": 20305
    },
    "amountUnit": 1000,
    "debit": {
      "formatted": "0",
      "amount": 0
    },
    "credit": {
      "formatted": "5,281,822",
      "amount": 5281821670
    }
  },
  {
    "account": {
      "accountCode": 20310
    },
    "amountUnit": 1000,
    "debit": {
      "formatted": "0",
      "amount": 0
    },
    "credit": {
      "formatted": "1,961,816",
      "amount": 1961816130
    }
  },
  {
    "account": {
      "accountCode": 20350
    },
    "amountUnit": 1000,
    "debit": {
      "formatted": "0",
      "amount": 0
    },
    "credit": {
      "formatted": "26,868,960",
      "amount": 26868960350
    }
  },
  {
    "account": {
      "accountCode": 20355
    },
    "amountUnit": 1000,
    "debit": {
      "formatted": "0",
      "amount": 0
    },
    "credit": {
      "formatted": "1,171,694",
      "amount": 1171694260
    }
  },
  {
    "account": {
      "accountCode": 20410
    },
    "amountUnit": 1000,
    "debit": {
      "formatted": "0",
      "amount": 0
    },
    "credit": {
      "formatted": "77,995,508",
      "amount": 77995508480
    }
  },
  {
    "account": {
      "accountCode": 20420
    },
    "amountUnit": 1000,
    "debit": {
      "formatted": "0",
      "amount": 0
    },
    "credit": {
      "formatted": "173,190,632",
      "amount": 173190632200
    }
  },
  {
    "account": {
      "accountCode": 20430
    },
    "amountUnit": 1000,
    "debit": {
      "formatted": "0",
      "amount": 0
    },
    "credit": {
      "formatted": "70,723",
      "amount": 70722920
    }
  },
  {
    "account": {
      "accountCode": 20440
    },
    "amountUnit": 1000,
    "debit": {
      "formatted": "0",
      "amount": 0
    },
    "credit": {
      "formatted": "60,000,000",
      "amount": 60000000000
    }
  },
  {
    "account": {
      "accountCode": 20450
    },
    "amountUnit": 1000,
    "debit": {
      "formatted": "0",
      "amount": 0
    },
    "credit": {
      "formatted": "24,981,000",
      "amount": 24981000000
    }
  },
  {
    "account": {
      "accountCode": 20455
    },
    "amountUnit": 1000,
    "debit": {
      "formatted": "0",
      "amount": 0
    },
    "credit": {
      "formatted": "0",
      "amount": 0
    }
  },
  {
    "account": {
      "accountCode": 20490
    },
    "amountUnit": 1000,
    "debit": {
      "formatted": "0",
      "amount": 0
    },
    "credit": {
      "formatted": "0",
      "amount": 0
    }
  },
  {
    "account": {
      "accountCode": 20495
    },
    "amountUnit": 1000,
    "debit": {
      "formatted": "0",
      "amount": 0
    },
    "credit": {
      "formatted": "0",
      "amount": 0
    }
  },
  {
    "account": {
      "accountCode": 20520
    },
    "amountUnit": 1000,
    "debit": {
      "formatted": "0",
      "amount": 0
    },
    "credit": {
      "formatted": "1,298,945",
      "amount": 1298944720
    }
  },
  {
    "account": {
      "accountCode": 20540
    },
    "amountUnit": 1000,
    "debit": {
      "formatted": "0",
      "amount": 0
    },
    "credit": {
      "formatted": "4,062,825",
      "amount": 4062824910
    }
  },
  {
    "account": {
      "accountCode": 20590
    },
    "amountUnit": 1000,
    "debit": {
      "formatted": "0",
      "amount": 0
    },
    "credit": {
      "formatted": "0",
      "amount": 0
    }
  },
  {
    "account": {
      "accountCode": 20685
    },
    "amountUnit": 1000,
    "debit": {
      "formatted": "637",
      "amount": 636990
    },
    "credit": {
      "formatted": "0",
      "amount": 0
    }
  },
  {
    "account": {
      "accountCode": 20687
    },
    "amountUnit": 1000,
    "debit": {
      "formatted": "0",
      "amount": 0
    },
    "credit": {
      "formatted": "0",
      "amount": 0
    }
  },
  {
    "account": {
      "accountCode": 21100
    },
    "amountUnit": 1000,
    "debit": {
      "formatted": "0",
      "amount": 0
    },
    "credit": {
      "formatted": "0",
      "amount": 0
    }
  },
  {
    "account": {
      "accountCode": 21110
    },
    "amountUnit": 1000,
    "debit": {
      "formatted": "0",
      "amount": 0
    },
    "credit": {
      "formatted": "0",
      "amount": 0
    }
  },
  {
    "account": {
      "accountCode": 21111
    },
    "amountUnit": 1000,
    "debit": {
      "formatted": "0",
      "amount": 0
    },
    "credit": {
      "formatted": "0",
      "amount": 0
    }
  },
  {
    "account": {
      "accountCode": 21120
    },
    "amountUnit": 1000,
    "debit": {
      "formatted": "0",
      "amount": 0
    },
    "credit": {
      "formatted": "0",
      "amount": 0
    }
  },
  {
    "account": {
      "accountCode": 21130
    },
    "amountUnit": 1000,
    "debit": {
      "formatted": "0",
      "amount": 0
    },
    "credit": {
      "formatted": "0",
      "amount": 0
    }
  },
  {
    "account": {
      "accountCode": 21140
    },
    "amountUnit": 1000,
    "debit": {
      "formatted": "0",
      "amount": 0
    },
    "credit": {
      "formatted": "0",
      "amount": 0
    }
  },
  {
    "account": {
      "accountCode": 21150
    },
    "amountUnit": 1000,
    "debit": {
      "formatted": "0",
      "amount": 0
    },
    "credit": {
      "formatted": "0",
      "amount": 0
    }
  },
  {
    "account": {
      "accountCode": 21180
    },
    "amountUnit": 1000,
    "debit": {
      "formatted": "0",
      "amount": 0
    },
    "credit": {
      "formatted": "0",
      "amount": 0
    }
  },
  {
    "account": {
      "accountCode": 21205
    },
    "amountUnit": 1000,
    "debit": {
      "formatted": "0",
      "amount": 0
    },
    "credit": {
      "formatted": "851",
      "amount": 851000
    }
  },
  {
    "account": {
      "accountCode": 21209
    },
    "amountUnit": 1000,
    "debit": {
      "formatted": "0",
      "amount": 0
    },
    "credit": {
      "formatted": "0",
      "amount": 0
    }
  },
  {
    "account": {
      "accountCode": 21210
    },
    "amountUnit": 1000,
    "debit": {
      "formatted": "0",
      "amount": 0
    },
    "credit": {
      "formatted": "17,886",
      "amount": 17886300
    }
  },
  {
    "account": {
      "accountCode": 21215
    },
    "amountUnit": 1000,
    "debit": {
      "formatted": "0",
      "amount": 0
    },
    "credit": {
      "formatted": "4,357",
      "amount": 4356850
    }
  },
  {
    "account": {
      "accountCode": 21217
    },
    "amountUnit": 1000,
    "debit": {
      "formatted": "0",
      "amount": 0
    },
    "credit": {
      "formatted": "48,467",
      "amount": 48466760
    }
  },
  {
    "account": {
      "accountCode": 21218
    },
    "amountUnit": 1000,
    "debit": {
      "formatted": "0",
      "amount": 0
    },
    "credit": {
      "formatted": "5,198",
      "amount": 5198370
    }
  },
  {
    "account": {
      "accountCode": 21219
    },
    "amountUnit": 1000,
    "debit": {
      "formatted": "0",
      "amount": 0
    },
    "credit": {
      "formatted": "1,373",
      "amount": 1373350
    }
  },
  {
    "account": {
      "accountCode": 21220
    },
    "amountUnit": 1000,
    "debit": {
      "formatted": "0",
      "amount": 0
    },
    "credit": {
      "formatted": "811",
      "amount": 811300
    }
  },
  {
    "account": {
      "accountCode": 21221
    },
    "amountUnit": 1000,
    "debit": {
      "formatted": "0",
      "amount": 0
    },
    "credit": {
      "formatted": "106,475",
      "amount": 106474690
    }
  },
  {
    "account": {
      "accountCode": 21223
    },
    "amountUnit": 1000,
    "debit": {
      "formatted": "0",
      "amount": 0
    },
    "credit": {
      "formatted": "2,164",
      "amount": 2163820
    }
  },
  {
    "account": {
      "accountCode": 21224
    },
    "amountUnit": 1000,
    "debit": {
      "formatted": "0",
      "amount": 0
    },
    "credit": {
      "formatted": "812",
      "amount": 812160
    }
  },
  {
    "account": {
      "accountCode": 21225
    },
    "amountUnit": 1000,
    "debit": {
      "formatted": "0",
      "amount": 0
    },
    "credit": {
      "formatted": "285,894",
      "amount": 285894190
    }
  },
  {
    "account": {
      "accountCode": 21230
    },
    "amountUnit": 1000,
    "debit": {
      "formatted": "0",
      "amount": 0
    },
    "credit": {
      "formatted": "594,446",
      "amount": 594446440
    }
  },
  {
    "account": {
      "accountCode": 21232
    },
    "amountUnit": 1000,
    "debit": {
      "formatted": "0",
      "amount": 0
    },
    "credit": {
      "formatted": "3,067",
      "amount": 3066670
    }
  },
  {
    "account": {
      "accountCode": 21233
    },
    "amountUnit": 1000,
    "debit": {
      "formatted": "0",
      "amount": 0
    },
    "credit": {
      "formatted": "1,323",
      "amount": 1323000
    }
  },
  {
    "account": {
      "accountCode": 21234
    },
    "amountUnit": 1000,
    "debit": {
      "formatted": "0",
      "amount": 0
    },
    "credit": {
      "formatted": "0",
      "amount": 0
    }
  },
  {
    "account": {
      "accountCode": 21235
    },
    "amountUnit": 1000,
    "debit": {
      "formatted": "0",
      "amount": 0
    },
    "credit": {
      "formatted": "5,827",
      "amount": 5826600
    }
  },
  {
    "account": {
      "accountCode": 21240
    },
    "amountUnit": 1000,
    "debit": {
      "formatted": "0",
      "amount": 0
    },
    "credit": {
      "formatted": "17,833",
      "amount": 17832790
    }
  },
  {
    "account": {
      "accountCode": 21290
    },
    "amountUnit": 1000,
    "debit": {
      "formatted": "0",
      "amount": 0
    },
    "credit": {
      "formatted": "0",
      "amount": 0
    }
  },
  {
    "account": {
      "accountCode": 21310
    },
    "amountUnit": 1000,
    "debit": {
      "formatted": "0",
      "amount": 0
    },
    "credit": {
      "formatted": "0",
      "amount": 0
    }
  },
  {
    "account": {
      "accountCode": 21320
    },
    "amountUnit": 1000,
    "debit": {
      "formatted": "0",
      "amount": 0
    },
    "credit": {
      "formatted": "0",
      "amount": 0
    }
  },
  {
    "account": {
      "accountCode": 21330
    },
    "amountUnit": 1000,
    "debit": {
      "formatted": "0",
      "amount": 0
    },
    "credit": {
      "formatted": "0",
      "amount": 0
    }
  },
  {
    "account": {
      "accountCode": 21340
    },
    "amountUnit": 1000,
    "debit": {
      "formatted": "0",
      "amount": 0
    },
    "credit": {
      "formatted": "0",
      "amount": 0
    }
  },
  {
    "account": {
      "accountCode": 21345
    },
    "amountUnit": 1000,
    "debit": {
      "formatted": "0",
      "amount": 0
    },
    "credit": {
      "formatted": "0",
      "amount": 0
    }
  },
  {
    "account": {
      "accountCode": 21350
    },
    "amountUnit": 1000,
    "debit": {
      "formatted": "0",
      "amount": 0
    },
    "credit": {
      "formatted": "0",
      "amount": 0
    }
  },
  {
    "account": {
      "accountCode": 21380
    },
    "amountUnit": 1000,
    "debit": {
      "formatted": "0",
      "amount": 0
    },
    "credit": {
      "formatted": "0",
      "amount": 0
    }
  },
  {
    "account": {
      "accountCode": 21410
    },
    "amountUnit": 1000,
    "debit": {
      "formatted": "0",
      "amount": 0
    },
    "credit": {
      "formatted": "496",
      "amount": 495890
    }
  },
  {
    "account": {
      "accountCode": 22110
    },
    "amountUnit": 1000,
    "debit": {
      "formatted": "0",
      "amount": 0
    },
    "credit": {
      "formatted": "0",
      "amount": 0
    }
  },
  {
    "account": {
      "accountCode": 22115
    },
    "amountUnit": 1000,
    "debit": {
      "formatted": "0",
      "amount": 0
    },
    "credit": {
      "formatted": "217,481",
      "amount": 217480780
    }
  },
  {
    "account": {
      "accountCode": 22120
    },
    "amountUnit": 1000,
    "debit": {
      "formatted": "0",
      "amount": 0
    },
    "credit": {
      "formatted": "148,012",
      "amount": 148011500
    }
  },
  {
    "account": {
      "accountCode": 22125
    },
    "amountUnit": 1000,
    "debit": {
      "formatted": "0",
      "amount": 0
    },
    "credit": {
      "formatted": "30,937",
      "amount": 30936770
    }
  },
  {
    "account": {
      "accountCode": 22126
    },
    "amountUnit": 1000,
    "debit": {
      "formatted": "0",
      "amount": 0
    },
    "credit": {
      "formatted": "752,925",
      "amount": 752924930
    }
  },
  {
    "account": {
      "accountCode": 22127
    },
    "amountUnit": 1000,
    "debit": {
      "formatted": "0",
      "amount": 0
    },
    "credit": {
      "formatted": "0",
      "amount": 0
    }
  },
  {
    "account": {
      "accountCode": 22128
    },
    "amountUnit": 1000,
    "debit": {
      "formatted": "0",
      "amount": 0
    },
    "credit": {
      "formatted": "0",
      "amount": 0
    }
  },
  {
    "account": {
      "accountCode": 22129
    },
    "amountUnit": 1000,
    "debit": {
      "formatted": "0",
      "amount": 0
    },
    "credit": {
      "formatted": "3,036",
      "amount": 3036310
    }
  },
  {
    "account": {
      "accountCode": 22130
    },
    "amountUnit": 1000,
    "debit": {
      "formatted": "0",
      "amount": 0
    },
    "credit": {
      "formatted": "1,289",
      "amount": 1289010
    }
  },
  {
    "account": {
      "accountCode": 22180
    },
    "amountUnit": 1000,
    "debit": {
      "formatted": "0",
      "amount": 0
    },
    "credit": {
      "formatted": "80,088",
      "amount": 80087840
    }
  },
  {
    "account": {
      "accountCode": 22185
    },
    "amountUnit": 1000,
    "debit": {
      "formatted": "0",
      "amount": 0
    },
    "credit": {
      "formatted": "29,292",
      "amount": 29292240
    }
  },
  {
    "account": {
      "accountCode": 22190
    },
    "amountUnit": 1000,
    "debit": {
      "formatted": "0",
      "amount": 0
    },
    "credit": {
      "formatted": "132,047",
      "amount": 132046570
    }
  },
  {
    "account": {
      "accountCode": 22191
    },
    "amountUnit": 1000,
    "debit": {
      "formatted": "0",
      "amount": 0
    },
    "credit": {
      "formatted": "144,313",
      "amount": 144312690
    }
  },
  {
    "account": {
      "accountCode": 22192
    },
    "amountUnit": 1000,
    "debit": {
      "formatted": "0",
      "amount": 0
    },
    "credit": {
      "formatted": "53,979",
      "amount": 53979180
    }
  },
  {
    "account": {
      "accountCode": 22193
    },
    "amountUnit": 1000,
    "debit": {
      "formatted": "0",
      "amount": 0
    },
    "credit": {
      "formatted": "68,964",
      "amount": 68964140
    }
  },
  {
    "account": {
      "accountCode": 22230
    },
    "amountUnit": 1000,
    "debit": {
      "formatted": "0",
      "amount": 0
    },
    "credit": {
      "formatted": "0",
      "amount": 0
    }
  },
  {
    "account": {
      "accountCode": 22240
    },
    "amountUnit": 1000,
    "debit": {
      "formatted": "0",
      "amount": 0
    },
    "credit": {
      "formatted": "2,043",
      "amount": 2042900
    }
  },
  {
    "account": {
      "accountCode": 22245
    },
    "amountUnit": 1000,
    "debit": {
      "formatted": "0",
      "amount": 0
    },
    "credit": {
      "formatted": "0",
      "amount": 0
    }
  },
  {
    "account": {
      "accountCode": 22250
    },
    "amountUnit": 1000,
    "debit": {
      "formatted": "0",
      "amount": 0
    },
    "credit": {
      "formatted": "0",
      "amount": 0
    }
  },
  {
    "account": {
      "accountCode": 22255
    },
    "amountUnit": 1000,
    "debit": {
      "formatted": "0",
      "amount": 0
    },
    "credit": {
      "formatted": "136,986",
      "amount": 136986320
    }
  },
  {
    "account": {
      "accountCode": 22260
    },
    "amountUnit": 1000,
    "debit": {
      "formatted": "0",
      "amount": 0
    },
    "credit": {
      "formatted": "0",
      "amount": 0
    }
  },
  {
    "account": {
      "accountCode": 22290
    },
    "amountUnit": 1000,
    "debit": {
      "formatted": "0",
      "amount": 0
    },
    "credit": {
      "formatted": "12,522",
      "amount": 12522280
    }
  },
  {
    "account": {
      "accountCode": 22295
    },
    "amountUnit": 1000,
    "debit": {
      "formatted": "0",
      "amount": 0
    },
    "credit": {
      "formatted": "0",
      "amount": 0
    }
  },
  {
    "account": {
      "accountCode": 22297
    },
    "amountUnit": 1000,
    "debit": {
      "formatted": "0",
      "amount": 0
    },
    "credit": {
      "formatted": "0",
      "amount": 0
    }
  },
  {
    "account": {
      "accountCode": 22310
    },
    "amountUnit": 1000,
    "debit": {
      "formatted": "0",
      "amount": 0
    },
    "credit": {
      "formatted": "0",
      "amount": 0
    }
  },
  {
    "account": {
      "accountCode": 22320
    },
    "amountUnit": 1000,
    "debit": {
      "formatted": "0",
      "amount": 0
    },
    "credit": {
      "formatted": "0",
      "amount": 0
    }
  },
  {
    "account": {
      "accountCode": 22430
    },
    "amountUnit": 1000,
    "debit": {
      "formatted": "0",
      "amount": 0
    },
    "credit": {
      "formatted": "2,707",
      "amount": 2707370
    }
  },
  {
    "account": {
      "accountCode": 22440
    },
    "amountUnit": 1000,
    "debit": {
      "formatted": "0",
      "amount": 0
    },
    "credit": {
      "formatted": "0",
      "amount": 0
    }
  },
  {
    "account": {
      "accountCode": 22480
    },
    "amountUnit": 1000,
    "debit": {
      "formatted": "0",
      "amount": 0
    },
    "credit": {
      "formatted": "3,555",
      "amount": 3554530
    }
  },
  {
    "account": {
      "accountCode": 22510
    },
    "amountUnit": 1000,
    "debit": {
      "formatted": "0",
      "amount": 0
    },
    "credit": {
      "formatted": "0",
      "amount": 0
    }
  },
  {
    "account": {
      "accountCode": 22610
    },
    "amountUnit": 1000,
    "debit": {
      "formatted": "0",
      "amount": 0
    },
    "credit": {
      "formatted": "51,291",
      "amount": 51291210
    }
  },
  {
    "account": {
      "accountCode": 22725
    },
    "amountUnit": 1000,
    "debit": {
      "formatted": "0",
      "amount": 0
    },
    "credit": {
      "formatted": "0",
      "amount": 0
    }
  },
  {
    "account": {
      "accountCode": 28110
    },
    "amountUnit": 1000,
    "debit": {
      "formatted": "0",
      "amount": 0
    },
    "credit": {
      "formatted": "31,138,497",
      "amount": 31138496630
    }
  },
  {
    "account": {
      "accountCode": 28120
    },
    "amountUnit": 1000,
    "debit": {
      "formatted": "0",
      "amount": 0
    },
    "credit": {
      "formatted": "53,678,359",
      "amount": 53678359300
    }
  },
  {
    "account": {
      "accountCode": 28125
    },
    "amountUnit": 1000,
    "debit": {
      "formatted": "0",
      "amount": 0
    },
    "credit": {
      "formatted": "0",
      "amount": 0
    }
  },
  {
    "account": {
      "accountCode": 28130
    },
    "amountUnit": 1000,
    "debit": {
      "formatted": "0",
      "amount": 0
    },
    "credit": {
      "formatted": "2,384,534",
      "amount": 2384534090
    }
  },
  {
    "account": {
      "accountCode": 28140
    },
    "amountUnit": 1000,
    "debit": {
      "formatted": "29,768,783",
      "amount": 29768782880
    },
    "credit": {
      "formatted": "0",
      "amount": 0
    }
  },
  {
    "account": {
      "accountCode": 28145
    },
    "amountUnit": 1000,
    "debit": {
      "formatted": "0",
      "amount": 0
    },
    "credit": {
      "formatted": "0",
      "amount": 0
    }
  },
  {
    "account": {
      "accountCode": 28150
    },
    "amountUnit": 1000,
    "debit": {
      "formatted": "0",
      "amount": 0
    },
    "credit": {
      "formatted": "22,834,917",
      "amount": 22834917120
    }
  },
  {
    "account": {
      "accountCode": 28160
    },
    "amountUnit": 1000,
    "debit": {
      "formatted": "825,274",
      "amount": 825274120
    },
    "credit": {
      "formatted": "0",
      "amount": 0
    }
  }
]