{
  "entities": [
    {
      "id": 1,
      "type": "Parent",
      "name": "사성디스플레이(주)",
      "location": "Korea",
      "currency": "KRW",
      "timeZone": "GMT+9",
      "coaId": "coa1"
    },
    {
      "id": 2,
      "type": "Subsidiary",
      "name": "사성물산(주)",
      "location": "Korea",
      "currency": "KRW",
      "timeZone": "GMT+9",
      "coaId": "coa2"
    },
    {
      "id": 3,
      "type": "Subsidiary",
      "name": "사성전기(주)",
      "location": "Korea",
      "currency": "KRW",
      "timeZone": "GMT+9",
      "coaId": null
    },
    {
      "id": 4,
      "type": "Subsidiary",
      "name": "사성행상(주)",
      "location": "Korea",
      "currency": "KRW",
      "timeZone": "GMT+9",
      "coaId": null
    }
  ],
  "fs-papers": [
    {
      "id": "12345_asdfsdfa",
      "type": "12345",
      "title": "asdfsdfa"
    },
    {
      "id": "12345sdfd_asdfssdsfsddfa",
      "type": "12345sdfd",
      "title": "asdfssdsfsddfa"
    }
  ],
  "chart-of-account": []
}